[
  {
    "name": "Teamsters National Homepage",
    "year": 2010,
    "displayUrl": "http://www.teamster.org:80/",
    "iframeUrl": "https://wayback.archive-it.org/4719/20100921101221/http://www.teamster.org:80/"
  },
  {
    "name": "Teamsters National Homepage",
    "year": 2002,
    "displayUrl": "http://www.teamster.org:80/",
    "iframeUrl": "https://wayback.archive-it.org/4719/20020716070123/http://www.teamster.org:80/"
  },
  {
    "name": "Teamsters National Homepage",
    "year": 2007,
    "displayUrl": "http://www.teamster.org:80/",
    "iframeUrl": "https://wayback.archive-it.org/4719/20070407193052/http://www.teamster.org:80/"
  },
  {
    "name": "Teamsters National Homepage",
    "year": 2013,
    "displayUrl": "http://www.teamster.org/",
    "iframeUrl": "https://wayback.archive-it.org/4719/20131203023944/http://www.teamster.org/"
  },
  {
    "name": "Teamsters National Homepage",
    "year": 2009,
    "displayUrl": "http://www.teamster.org:80/",
    "iframeUrl": "https://wayback.archive-it.org/4719/20090319083338/http://www.teamster.org:80/"
  },
  {
    "name": "Teamsters National Homepage",
    "year": 2008,
    "displayUrl": "http://www.teamster.org/",
    "iframeUrl": "https://wayback.archive-it.org/4719/20080905150757/http://www.teamster.org/"
  },
  {
    "name": "Teamsters National Homepage",
    "year": 2002,
    "displayUrl": "http://www.teamster.org:80/",
    "iframeUrl": "https://wayback.archive-it.org/4719/20021011071435/http://www.teamster.org:80/"
  },
  {
    "name": "Teamsters National Homepage",
    "year": 2021,
    "displayUrl": "https://teamster.org/",
    "iframeUrl": "https://wayback.archive-it.org/4719/20210506224748/https://teamster.org/"
  },
  {
    "name": "Teamsters National Homepage",
    "year": 2001,
    "displayUrl": "http://www.teamster.org:80/",
    "iframeUrl": "https://wayback.archive-it.org/4719/20011206220721/http://www.teamster.org:80/"
  },
  {
    "name": "Teamsters National Homepage",
    "year": 2005,
    "displayUrl": "http://www.teamster.org:80/",
    "iframeUrl": "https://wayback.archive-it.org/4719/20050615073856/http://www.teamster.org:80/"
  },
  {
    "name": "Teamsters National Homepage",
    "year": 2006,
    "displayUrl": "http://www.teamster.org:80/",
    "iframeUrl": "https://wayback.archive-it.org/4719/20060701051611/http://www.teamster.org:80/"
  },
  {
    "name": "Teamsters National Homepage",
    "year": 2005,
    "displayUrl": "http://www.teamster.org:80/",
    "iframeUrl": "https://wayback.archive-it.org/4719/20050708081531/http://www.teamster.org:80/"
  },
  {
    "name": "Teamsters National Homepage",
    "year": 2005,
    "displayUrl": "http://www.teamster.org:80/",
    "iframeUrl": "https://wayback.archive-it.org/4719/20050826173505/http://www.teamster.org:80/"
  },
  {
    "name": "Teamsters National Homepage",
    "year": 2005,
    "displayUrl": "http://www.teamster.org:80/",
    "iframeUrl": "https://wayback.archive-it.org/4719/20050626013624/http://www.teamster.org:80/"
  },
  {
    "name": "Teamsters National Homepage",
    "year": 2007,
    "displayUrl": "http://www.teamster.org/",
    "iframeUrl": "https://wayback.archive-it.org/4719/20070330181347/http://www.teamster.org/"
  },
  {
    "name": "Teamsters National Homepage",
    "year": 2010,
    "displayUrl": "http://www.teamster.org:80/",
    "iframeUrl": "https://wayback.archive-it.org/4719/20101018015133/http://www.teamster.org:80/"
  },
  {
    "name": "Teamsters National Homepage",
    "year": 2011,
    "displayUrl": "http://www.teamster.org/",
    "iframeUrl": "https://wayback.archive-it.org/4719/20110728035451/http://www.teamster.org/"
  },
  {
    "name": "Teamsters National Homepage",
    "year": 2006,
    "displayUrl": "http://www.teamster.org:80/",
    "iframeUrl": "https://wayback.archive-it.org/4719/20060202022757/http://www.teamster.org:80/"
  },
  {
    "name": "Teamsters National Homepage",
    "year": 2011,
    "displayUrl": "http://www.teamster.org/",
    "iframeUrl": "https://wayback.archive-it.org/4719/20110509211051/http://www.teamster.org/"
  },
  {
    "name": "Teamsters National Homepage",
    "year": 2001,
    "displayUrl": "http://www.teamster.org:80/",
    "iframeUrl": "https://wayback.archive-it.org/4719/20011109220041/http://www.teamster.org:80/"
  },
  {
    "name": "Teamsters National Homepage",
    "year": 2002,
    "displayUrl": "http://www.teamster.org:80/",
    "iframeUrl": "https://wayback.archive-it.org/4719/20021121074221/http://www.teamster.org:80/"
  },
  {
    "name": "Teamsters National Homepage",
    "year": 2013,
    "displayUrl": "http://www.teamster.org:80/",
    "iframeUrl": "https://wayback.archive-it.org/4719/20130902184807/http://www.teamster.org:80/"
  },
  {
    "name": "Teamsters National Homepage",
    "year": 2008,
    "displayUrl": "http://www.teamster.org:80/",
    "iframeUrl": "https://wayback.archive-it.org/4719/20080227005147/http://www.teamster.org:80/"
  },
  {
    "name": "Teamsters National Homepage",
    "year": 2008,
    "displayUrl": "http://www.teamster.org/",
    "iframeUrl": "https://wayback.archive-it.org/4719/20081022231424/http://www.teamster.org/"
  },
  {
    "name": "Teamsters National Homepage",
    "year": 2001,
    "displayUrl": "http://www.teamster.org:80/",
    "iframeUrl": "https://wayback.archive-it.org/4719/20011127041130/http://www.teamster.org:80/"
  },
  {
    "name": "Teamsters National Homepage",
    "year": 2014,
    "displayUrl": "http://teamster.org/",
    "iframeUrl": "https://wayback.archive-it.org/4719/20140405050127/http://teamster.org/"
  },
  {
    "name": "Teamsters National Homepage",
    "year": 2002,
    "displayUrl": "http://www.teamster.org:80/",
    "iframeUrl": "https://wayback.archive-it.org/4719/20020820071353/http://www.teamster.org:80/"
  },
  {
    "name": "Teamsters National Homepage",
    "year": 2001,
    "displayUrl": "http://www.teamster.org:80/",
    "iframeUrl": "https://wayback.archive-it.org/4719/20010418150602/http://www.teamster.org:80/"
  },
  {
    "name": "Teamsters National Homepage",
    "year": 2002,
    "displayUrl": "http://www.teamster.org:80/",
    "iframeUrl": "https://wayback.archive-it.org/4719/20020725070458/http://www.teamster.org:80/"
  },
  {
    "name": "Teamsters National Homepage",
    "year": 2005,
    "displayUrl": "http://www.teamster.org:80/",
    "iframeUrl": "https://wayback.archive-it.org/4719/20050609000313/http://www.teamster.org:80/"
  },
  {
    "name": "Teamsters National Homepage",
    "year": 2007,
    "displayUrl": "http://www.teamster.org:80/",
    "iframeUrl": "https://wayback.archive-it.org/4719/20070127023550/http://www.teamster.org:80/"
  },
  {
    "name": "Teamsters National Homepage",
    "year": 2009,
    "displayUrl": "http://www.teamster.org:80/",
    "iframeUrl": "https://wayback.archive-it.org/4719/20091003092122/http://www.teamster.org:80/"
  },
  {
    "name": "Teamsters National Homepage",
    "year": 2002,
    "displayUrl": "http://www.teamster.org:80/",
    "iframeUrl": "https://wayback.archive-it.org/4719/20020724070427/http://www.teamster.org:80/"
  },
  {
    "name": "Teamsters National Homepage",
    "year": 2013,
    "displayUrl": "http://www.teamster.org:80/?",
    "iframeUrl": "https://wayback.archive-it.org/4719/20130106180256/http://www.teamster.org:80/?"
  },
  {
    "name": "Teamsters National Homepage",
    "year": 2002,
    "displayUrl": "http://www.teamster.org:80/",
    "iframeUrl": "https://wayback.archive-it.org/4719/20021110082954/http://www.teamster.org:80/"
  },
  {
    "name": "Teamsters National Homepage",
    "year": 2006,
    "displayUrl": "http://www.teamster.org/",
    "iframeUrl": "https://wayback.archive-it.org/4719/20060920234619/http://www.teamster.org/"
  },
  {
    "name": "Teamsters National Homepage",
    "year": 2014,
    "displayUrl": "http://teamster.org/",
    "iframeUrl": "https://wayback.archive-it.org/4719/20140114031849/http://teamster.org/"
  },
  {
    "name": "Teamsters National Homepage",
    "year": 2006,
    "displayUrl": "http://www.teamster.org:80/",
    "iframeUrl": "https://wayback.archive-it.org/4719/20060409201539/http://www.teamster.org:80/"
  },
  {
    "name": "Teamsters National Homepage",
    "year": 2005,
    "displayUrl": "http://www.teamster.org:80/",
    "iframeUrl": "https://wayback.archive-it.org/4719/20050720073330/http://www.teamster.org:80/"
  },
  {
    "name": "Teamsters National Homepage",
    "year": 2001,
    "displayUrl": "http://www.teamster.org:80/",
    "iframeUrl": "https://wayback.archive-it.org/4719/20010617025950/http://www.teamster.org:80/"
  },
  {
    "name": "Teamsters National Homepage",
    "year": 2005,
    "displayUrl": "http://www.teamster.org:80/",
    "iframeUrl": "https://wayback.archive-it.org/4719/20050507090920/http://www.teamster.org:80/"
  },
  {
    "name": "Teamsters National Homepage",
    "year": 2002,
    "displayUrl": "http://www.teamster.org:80/",
    "iframeUrl": "https://wayback.archive-it.org/4719/20020830213855/http://www.teamster.org:80/"
  },
  {
    "name": "Teamsters National Homepage",
    "year": 2009,
    "displayUrl": "http://www.teamster.org:80/",
    "iframeUrl": "https://wayback.archive-it.org/4719/20090226045352/http://www.teamster.org:80/"
  },
  {
    "name": "Teamsters National Homepage",
    "year": 2010,
    "displayUrl": "http://www.teamster.org:80/",
    "iframeUrl": "https://wayback.archive-it.org/4719/20101129061640/http://www.teamster.org:80/"
  },
  {
    "name": "Teamsters National Homepage",
    "year": 2006,
    "displayUrl": "http://www.teamster.org:80/",
    "iframeUrl": "https://wayback.archive-it.org/4719/20060104160322/http://www.teamster.org:80/"
  },
  {
    "name": "Teamsters National Homepage",
    "year": 2005,
    "displayUrl": "http://www.teamster.org:80/",
    "iframeUrl": "https://wayback.archive-it.org/4719/20050829194609/http://www.teamster.org:80/"
  },
  {
    "name": "Teamsters National Homepage",
    "year": 2006,
    "displayUrl": "http://www.teamster.org:80/",
    "iframeUrl": "https://wayback.archive-it.org/4719/20060423020722/http://www.teamster.org:80/"
  },
  {
    "name": "Teamsters National Homepage",
    "year": 2007,
    "displayUrl": "http://www.teamster.org/",
    "iframeUrl": "https://wayback.archive-it.org/4719/20070927204349/http://www.teamster.org/"
  },
  {
    "name": "Teamsters National Homepage",
    "year": 2001,
    "displayUrl": "http://www.teamster.org:80/",
    "iframeUrl": "https://wayback.archive-it.org/4719/20011112013647/http://www.teamster.org:80/"
  },
  {
    "name": "Teamsters National Homepage",
    "year": 2005,
    "displayUrl": "http://www.teamster.org:80/",
    "iframeUrl": "https://wayback.archive-it.org/4719/20050727020837/http://www.teamster.org:80/"
  }
]